[{"id":1,"label":"993 7th Lane","description":"Kendalrejo","country":"Indonesia"},
{"id":2,"label":"3 Vernon Plaza","description":"Itaí","country":"Brazil"},
{"id":3,"label":"883 Northfield Pass","description":"Boro Utara","country":"Indonesia"},
{"id":4,"label":"77821 Trailsway Circle","description":"Igaraçu do Tietê","country":"Brazil"},
{"id":5,"label":"6 Hauk Lane","description":"Tupaciguara","country":"Brazil"},
{"id":6,"label":"43 Del Mar Hill","description":"Nanlang","country":"China"},
{"id":7,"label":"43 Johnson Parkway","description":"Bang Racham","country":"Thailand"},
{"id":8,"label":"0789 Tomscot Terrace","description":"Mértola","country":"Portugal"},
{"id":9,"label":"4624 Thierer Trail","description":"Qidu","country":"China"},
{"id":10,"label":"7553 Schlimgen Court","description":"Kenyau","country":"Indonesia"},
{"id":11,"label":"1 Esch Parkway","description":"Guimarães","country":"Portugal"},
{"id":12,"label":"37 Sachtjen Lane","description":"Pickering","country":"Canada"},
{"id":13,"label":"0091 Little Fleur Road","description":"Modderfontein","country":"South Africa"},
{"id":14,"label":"44 Lillian Trail","description":"San Juan","country":"Puerto Rico"},
{"id":15,"label":"7 Laurel Park","description":"Fujiayan","country":"China"},
{"id":16,"label":"014 Lakeland Junction","description":"Wenping","country":"China"},
{"id":17,"label":"86900 American Center","description":"Stockholm","country":"Sweden"},
{"id":18,"label":"226 Lawn Junction","description":"Narathiwat","country":"Thailand"},
{"id":19,"label":"1397 Chinook Hill","description":"Grytviken","country":"South Georgia and the South Sandwich Islands"},
{"id":20,"label":"377 Fieldstone Trail","description":"Benešov nad Ploučnicí","country":"Czech Republic"},
{"id":21,"label":"505 Lukken Lane","description":"El Valle del Espíritu Santo","country":"Venezuela"},
{"id":22,"label":"29 Montana Park","description":"Amadora","country":"Portugal"},
{"id":23,"label":"6274 North Terrace","description":"Bilo","country":"Indonesia"},
{"id":24,"label":"7741 Hooker Lane","description":"Tairan Camp","country":"Philippines"},
{"id":25,"label":"5123 Hayes Plaza","description":"Medellín","country":"Colombia"},
{"id":26,"label":"2 La Follette Drive","description":"Río Ceballos","country":"Argentina"},
{"id":27,"label":"024 Utah Park","description":"Kiffa","country":"Mauritania"},
{"id":28,"label":"4 Darwin Trail","description":"Donggaocun","country":"China"},
{"id":29,"label":"77 Sheridan Plaza","description":"Limbuš","country":"Slovenia"},
{"id":30,"label":"5 Forest Dale Trail","description":"Bangonay","country":"Philippines"},
{"id":31,"label":"52835 Everett Hill","description":"Aygestan","country":"Armenia"},
{"id":32,"label":"7 Golf View Lane","description":"Warnes","country":"Bolivia"},
{"id":33,"label":"03583 Bonner Drive","description":"Tongqian","country":"China"},
{"id":34,"label":"46963 Quincy Road","description":"Hengtang","country":"China"},
{"id":35,"label":"586 6th Lane","description":"Johor Bahru","country":"Malaysia"},
{"id":36,"label":"8816 Hoard Junction","description":"Santa Adélia","country":"Brazil"},
{"id":37,"label":"2158 Graedel Alley","description":"Sekolan","country":"Indonesia"},
{"id":38,"label":"62037 Northport Terrace","description":"Huyunxiang","country":"China"},
{"id":39,"label":"8 Prentice Road","description":"Ziroudani","country":"Comoros"},
{"id":40,"label":"9 Express Hill","description":"Jinshandian","country":"China"},
{"id":41,"label":"6622 Claremont Hill","description":"Antipino","country":"Russia"},
{"id":42,"label":"98953 Forest Parkway","description":"Perovo","country":"Russia"},
{"id":43,"label":"10924 Grasskamp Drive","description":"Zhangdian","country":"China"},
{"id":44,"label":"79 Garrison Circle","description":"Rodez","country":"France"},
{"id":45,"label":"15 7th Plaza","description":"Eman","country":"China"},
{"id":46,"label":"07312 Troy Pass","description":"Kudamatsu","country":"Japan"},
{"id":47,"label":"7 Center Park","description":"Jamaica","country":"United States"},
{"id":48,"label":"34243 Morning Lane","description":"Al ‘Aqabah","country":"Yemen"},
{"id":49,"label":"390 Goodland Park","description":"Bandeirantes","country":"Brazil"},
{"id":50,"label":"2 Prairie Rose Place","description":"Tonkino","country":"Russia"},
{"id":51,"label":"0312 Old Shore Road","description":"Maebashi-shi","country":"Japan"},
{"id":52,"label":"7 Parkside Junction","description":"Barranquilla","country":"Colombia"},
{"id":53,"label":"96 Dapin Point","description":"Sumalig","country":"Philippines"},
{"id":54,"label":"59442 Charing Cross Center","description":"Vesele","country":"Ukraine"},
{"id":55,"label":"8022 Northport Park","description":"Heshan","country":"China"},
{"id":56,"label":"209 Old Gate Center","description":"Pelabuhan Dagang","country":"Indonesia"},
{"id":57,"label":"5 Hagan Avenue","description":"Kuragaki-kosugi","country":"Japan"},
{"id":58,"label":"96 Roth Point","description":"Kortowo","country":"Poland"},
{"id":59,"label":"92 Welch Circle","description":"Shuitian","country":"China"},
{"id":60,"label":"40135 Northwestern Park","description":"Aparecida do Taboado","country":"Brazil"},
{"id":61,"label":"22 Moulton Pass","description":"Port-Gentil","country":"Gabon"},
{"id":62,"label":"0 Dunning Trail","description":"Halinów","country":"Poland"},
{"id":63,"label":"76088 Susan Hill","description":"Makbon","country":"Indonesia"},
{"id":64,"label":"0122 Comanche Court","description":"Kanye","country":"Botswana"},
{"id":65,"label":"0545 Sunfield Junction","description":"Nishor","country":"Kosovo"},
{"id":66,"label":"90 Sommers Park","description":"Rokiškis","country":"Lithuania"},
{"id":67,"label":"25 Esch Lane","description":"El Calvario","country":"Mexico"},
{"id":68,"label":"78 Jenifer Park","description":"Besançon","country":"France"},
{"id":69,"label":"2 Pawling Street","description":"Pontang Tengah","country":"Indonesia"},
{"id":70,"label":"83871 Iowa Terrace","description":"Monte Novo","country":"Portugal"},
{"id":71,"label":"43 Surrey Crossing","description":"Ludvika","country":"Sweden"},
{"id":72,"label":"065 Prairie Rose Terrace","description":"El Calvario","country":"Mexico"},
{"id":73,"label":"8 Prairieview Park","description":"Trindade","country":"Brazil"},
{"id":74,"label":"89 Declaration Hill","description":"Stírion","country":"Greece"},
{"id":75,"label":"3 Kropf Street","description":"Lisków","country":"Poland"},
{"id":76,"label":"6434 Forest Run Junction","description":"Jaguarão","country":"Brazil"},
{"id":77,"label":"27 Fuller Park","description":"Jiuting","country":"China"},
{"id":78,"label":"82511 Ridge Oak Park","description":"Zhanghekou","country":"China"},
{"id":79,"label":"320 Loeprich Point","description":"Harembo","country":"Comoros"},
{"id":80,"label":"60812 Oakridge Parkway","description":"Klokot","country":"Kosovo"},
{"id":81,"label":"709 Iowa Road","description":"Dikwa","country":"Nigeria"},
{"id":82,"label":"1086 Cottonwood Trail","description":"Al Hadā","country":"Saudi Arabia"},
{"id":83,"label":"77906 Mandrake Parkway","description":"Meixian","country":"China"},
{"id":84,"label":"95 Oak Valley Center","description":"El Ángel","country":"Ecuador"},
{"id":85,"label":"171 Farwell Street","description":"Henghe","country":"China"},
{"id":86,"label":"8 Raven Avenue","description":"Bayan-Ovoo","country":"Mongolia"},
{"id":87,"label":"37 Talmadge Way","description":"Chicago","country":"United States"},
{"id":88,"label":"84321 Manufacturers Road","description":"Leżajsk","country":"Poland"},
{"id":89,"label":"35 Steensland Lane","description":"Krajan Karanganyar","country":"Indonesia"},
{"id":90,"label":"113 Magdeline Park","description":"Alcalá","country":"Colombia"},
{"id":91,"label":"10 Colorado Park","description":"Nový Hrozenkov","country":"Czech Republic"},
{"id":92,"label":"4018 Katie Pass","description":"Gryfów Śląski","country":"Poland"},
{"id":93,"label":"5967 Lyons Pass","description":"Duas Igrejas","country":"Portugal"},
{"id":94,"label":"49 Norway Maple Hill","description":"Magdalena","country":"Philippines"},
{"id":95,"label":"59 Straubel Plaza","description":"Bagou","country":"China"},
{"id":96,"label":"0 Bellgrove Center","description":"Gangmian","country":"China"},
{"id":97,"label":"2 Golf Course Plaza","description":"Santo Domingo Este","country":"Dominican Republic"},
{"id":98,"label":"9606 Lawn Trail","description":"San Carlos de Bariloche","country":"Argentina"},
{"id":99,"label":"2 Lerdahl Trail","description":"Dal’neye Konstantinovo","country":"Russia"},
{"id":100,"label":"3 Mifflin Junction","description":"Piraquara","country":"Brazil"},
{"id":101,"label":"48355 Florence Place","description":"Sebewe","country":"Indonesia"},
{"id":102,"label":"41 Weeping Birch Lane","description":"Weizhou","country":"China"},
{"id":103,"label":"606 Novick Center","description":"Wongaya Kaja","country":"Indonesia"},
{"id":104,"label":"11516 Killdeer Court","description":"Uacon","country":"Philippines"},
{"id":105,"label":"60149 Kim Lane","description":"Beichengqu","country":"China"},
{"id":106,"label":"42 Eliot Trail","description":"Heka","country":"China"},
{"id":107,"label":"11 Maywood Pass","description":"Ferreira do Zêzere","country":"Portugal"},
{"id":108,"label":"107 Donald Way","description":"Banisilan","country":"Philippines"},
{"id":109,"label":"395 Debs Drive","description":"Valença do Douro","country":"Portugal"},
{"id":110,"label":"65234 Graedel Street","description":"Khirdalan","country":"Azerbaijan"},
{"id":111,"label":"944 Drewry Center","description":"Gampola","country":"Sri Lanka"},
{"id":112,"label":"2 Magdeline Court","description":"Xiachengzi","country":"China"},
{"id":113,"label":"24178 Northport Point","description":"Johogunung","country":"Indonesia"},
{"id":114,"label":"47 John Wall Parkway","description":"Daşoguz","country":"Turkmenistan"},
{"id":115,"label":"65 Miller Circle","description":"Kiruna","country":"Sweden"},
{"id":116,"label":"14042 Dryden Hill","description":"Zambrów","country":"Poland"},
{"id":117,"label":"966 Lakewood Gardens Court","description":"Tanenofunan","country":"Indonesia"},
{"id":118,"label":"1 Scoville Street","description":"Akashi","country":"Japan"},
{"id":119,"label":"65 Fisk Pass","description":"Udachny","country":"Russia"},
{"id":120,"label":"70 Lotheville Way","description":"María la Baja","country":"Colombia"},
{"id":121,"label":"48417 Manufacturers Road","description":"Rushanzhai","country":"China"},
{"id":122,"label":"695 8th Circle","description":"Dongpu","country":"China"},
{"id":123,"label":"83538 Anzinger Circle","description":"Skien","country":"Norway"},
{"id":124,"label":"5 Bartelt Plaza","description":"Mabamba","country":"Tanzania"},
{"id":125,"label":"907 Victoria Court","description":"Colonia Yguazú","country":"Paraguay"},
{"id":126,"label":"0 Merrick Junction","description":"Dongla","country":"China"},
{"id":127,"label":"223 Portage Terrace","description":"Almargem do Bispo","country":"Portugal"},
{"id":128,"label":"4 Arizona Lane","description":"Bangonay","country":"Philippines"},
{"id":129,"label":"17007 Sloan Road","description":"Kholm","country":"Russia"},
{"id":130,"label":"69009 Hanson Center","description":"Yeniköy","country":"Turkey"},
{"id":131,"label":"93 Golden Leaf Park","description":"Mazra‘at Bayt Jinn","country":"Syria"},
{"id":132,"label":"2 Sage Junction","description":"Lab","country":"China"},
{"id":133,"label":"472 Killdeer Way","description":"Henan’an","country":"China"},
{"id":134,"label":"8836 Mosinee Trail","description":"Huangsangkou","country":"China"},
{"id":135,"label":"71011 Huxley Lane","description":"Bay-ang","country":"Philippines"},
{"id":136,"label":"44 Little Fleur Center","description":"Zaragoza","country":"Guatemala"},
{"id":137,"label":"77864 Mariners Cove Court","description":"Anibare","country":"Nauru"},
{"id":138,"label":"400 Manitowish Pass","description":"Taikang","country":"China"},
{"id":139,"label":"59 Basil Parkway","description":"Jagabaya Dua","country":"Indonesia"},
{"id":140,"label":"729 Menomonie Drive","description":"Yuza","country":"Japan"},
{"id":141,"label":"5842 Porter Alley","description":"Shuinan","country":"China"},
{"id":142,"label":"7 Towne Court","description":"Genisséa","country":"Greece"},
{"id":143,"label":"06 Graceland Street","description":"Mauraro","country":"Philippines"},
{"id":144,"label":"101 Elka Terrace","description":"Yinxi","country":"China"},
{"id":145,"label":"417 Debra Drive","description":"Lysekil","country":"Sweden"},
{"id":146,"label":"4 Veith Circle","description":"Jinsha","country":"China"},
{"id":147,"label":"5 Graceland Court","description":"Arsenal","country":"Mauritius"},
{"id":148,"label":"0194 Gina Road","description":"Aldeia","country":"Portugal"},
{"id":149,"label":"60642 Waywood Junction","description":"Hupalivka","country":"Ukraine"},
{"id":150,"label":"03 Tennessee Pass","description":"Paris 16","country":"France"},
{"id":151,"label":"365 Express Alley","description":"Kibiti","country":"Tanzania"},
{"id":152,"label":"0 Victoria Terrace","description":"Shuikou","country":"China"},
{"id":153,"label":"57944 Elka Plaza","description":"Qaţanah","country":"Palestinian Territory"},
{"id":154,"label":"72 Gina Court","description":"Carahue","country":"Chile"},
{"id":155,"label":"599 Coleman Lane","description":"Shinao","country":"China"},
{"id":156,"label":"40 Northland Court","description":"Hirosaki","country":"Japan"},
{"id":157,"label":"63538 Continental Terrace","description":"Kuala Terengganu","country":"Malaysia"},
{"id":158,"label":"001 Algoma Road","description":"Áno Kopanákion","country":"Greece"},
{"id":159,"label":"23 Lakewood Gardens Hill","description":"Sindangrasa","country":"Indonesia"},
{"id":160,"label":"93 Corben Park","description":"Yablochnyy","country":"Russia"},
{"id":161,"label":"729 Hoard Road","description":"Khagrachhari","country":"Bangladesh"},
{"id":162,"label":"3 Fieldstone Street","description":"Nanling","country":"China"},
{"id":163,"label":"77 Victoria Terrace","description":"Saint Lucia","country":"Malta"},
{"id":164,"label":"82 Little Fleur Way","description":"Meiyuan","country":"China"},
{"id":165,"label":"0810 Mallory Pass","description":"Verkhniy Rohachyk","country":"Ukraine"},
{"id":166,"label":"3 Dennis Drive","description":"Babahoyo","country":"Ecuador"},
{"id":167,"label":"2670 Lotheville Road","description":"Gaoqiu","country":"China"},
{"id":168,"label":"875 Anthes Circle","description":"Lokoja","country":"Nigeria"},
{"id":169,"label":"66 Old Shore Terrace","description":"Weichanglu","country":"China"},
{"id":170,"label":"46 Trailsway Street","description":"Sifala","country":"Indonesia"},
{"id":171,"label":"782 Cottonwood Drive","description":"Buensuseso","country":"Philippines"},
{"id":172,"label":"72551 Ilene Hill","description":"Presidencia Roque Sáenz Peña","country":"Argentina"},
{"id":173,"label":"00187 Mayer Point","description":"Culeng","country":"Indonesia"},
{"id":174,"label":"901 Summerview Alley","description":"Budapest","country":"Hungary"},
{"id":175,"label":"22120 Carpenter Center","description":"Homeyo","country":"Indonesia"},
{"id":176,"label":"77 Schiller Crossing","description":"Khon San","country":"Thailand"},
{"id":177,"label":"3 Colorado Junction","description":"Saparbay","country":"China"},
{"id":178,"label":"686 Oxford Court","description":"Arjona","country":"Colombia"},
{"id":179,"label":"8 Schurz Crossing","description":"Trondheim","country":"Norway"},
{"id":180,"label":"46388 Arrowood Junction","description":"Kon Tum","country":"Vietnam"},
{"id":181,"label":"0915 Sauthoff Park","description":"Lipsko","country":"Poland"},
{"id":182,"label":"5044 Morningstar Alley","description":"Seattle","country":"United States"},
{"id":183,"label":"059 Chive Drive","description":"Tibakisa","country":"Indonesia"},
{"id":184,"label":"45513 Jay Alley","description":"Chengjiao","country":"China"},
{"id":185,"label":"238 Fairview Avenue","description":"Lagarto","country":"Brazil"},
{"id":186,"label":"163 Welch Street","description":"Cabugao","country":"Philippines"},
{"id":187,"label":"48491 Dorton Circle","description":"Kalān Deh","country":"Afghanistan"},
{"id":188,"label":"616 Tomscot Pass","description":"Emporeío","country":"Greece"},
{"id":189,"label":"0 Moulton Drive","description":"Calvaria de Baixo","country":"Portugal"},
{"id":190,"label":"53343 Dunning Parkway","description":"Montréal-Est","country":"Canada"},
{"id":191,"label":"1987 Acker Terrace","description":"Kibiti","country":"Tanzania"},
{"id":192,"label":"5 Eagle Crest Hill","description":"Kassándreia","country":"Greece"},
{"id":193,"label":"32 Merry Hill","description":"Ojrzeń","country":"Poland"},
{"id":194,"label":"228 Welch Road","description":"Marinha","country":"Portugal"},
{"id":195,"label":"1 Prentice Drive","description":"Isangel","country":"Vanuatu"},
{"id":196,"label":"1 South Alley","description":"Karangsono","country":"Indonesia"},
{"id":197,"label":"6759 Victoria Road","description":"Perivólia","country":"Cyprus"},
{"id":198,"label":"4502 Lotheville Lane","description":"Tiên Phước","country":"Vietnam"},
{"id":199,"label":"49 Evergreen Park","description":"Candi Prambanan","country":"Indonesia"},
{"id":200,"label":"5 Dwight Parkway","description":"Sigma","country":"Philippines"},
{"id":201,"label":"14695 Iowa Terrace","description":"Sindanghayu","country":"Indonesia"},
{"id":202,"label":"76499 Grover Road","description":"Chignayhua","country":"Peru"},
{"id":203,"label":"404 Gina Circle","description":"Medeiros Neto","country":"Brazil"},
{"id":204,"label":"18 Upham Pass","description":"Algarvia","country":"Portugal"},
{"id":205,"label":"7 Dovetail Pass","description":"Andrézieux-Bouthéon","country":"France"},
{"id":206,"label":"58192 Packers Point","description":"Vuhlehirs’k","country":"Ukraine"},
{"id":207,"label":"08 Sherman Road","description":"North Side","country":"Cayman Islands"},
{"id":208,"label":"89344 Mariners Cove Avenue","description":"Martigues","country":"France"},
{"id":209,"label":"60047 Delladonna Point","description":"Namysłów","country":"Poland"},
{"id":210,"label":"47178 Northport Center","description":"Vaiamonte","country":"Portugal"},
{"id":211,"label":"1810 Namekagon Park","description":"Portelândia","country":"Brazil"},
{"id":212,"label":"9663 Merrick Park","description":"Bauru","country":"Brazil"},
{"id":213,"label":"1487 Pepper Wood Point","description":"Gharavŭtí","country":"Tajikistan"},
{"id":214,"label":"48 Loomis Parkway","description":"Tullinge","country":"Sweden"},
{"id":215,"label":"72543 Clemons Point","description":"Lajedo","country":"Brazil"},
{"id":216,"label":"72 Bonner Point","description":"Kristianstad","country":"Sweden"},
{"id":217,"label":"83604 Golden Leaf Point","description":"Ra’s Bayrūt","country":"Lebanon"},
{"id":218,"label":"4 Bashford Road","description":"Phetchaburi","country":"Thailand"},
{"id":219,"label":"4 Sycamore Court","description":"La Eduvigis","country":"Argentina"},
{"id":220,"label":"04943 Grayhawk Trail","description":"Ogurugu","country":"Nigeria"},
{"id":221,"label":"91 Grover Plaza","description":"Bluefields","country":"Jamaica"},
{"id":222,"label":"77545 Welch Junction","description":"Nawá","country":"Syria"},
{"id":223,"label":"06405 Calypso Park","description":"Watari","country":"Japan"},
{"id":224,"label":"163 Bluestem Terrace","description":"Suzano","country":"Brazil"},
{"id":225,"label":"47 Del Sol Crossing","description":"Linshui","country":"China"},
{"id":226,"label":"5 Monterey Drive","description":"Calebasses","country":"Mauritius"},
{"id":227,"label":"0671 Pearson Plaza","description":"Madala","country":"Nigeria"},
{"id":228,"label":"05037 Arizona Lane","description":"Mchinji","country":"Malawi"},
{"id":229,"label":"39718 Sommers Park","description":"Isniq","country":"Kosovo"},
{"id":230,"label":"46958 Lerdahl Junction","description":"Ljubno ob Savinji","country":"Slovenia"},
{"id":231,"label":"00213 Columbus Parkway","description":"Steinkjer","country":"Norway"},
{"id":232,"label":"0177 Ludington Junction","description":"Fada","country":"Chad"},
{"id":233,"label":"081 Pepper Wood Street","description":"Mae Lao","country":"Thailand"},
{"id":234,"label":"9913 Pawling Pass","description":"Aurora","country":"Philippines"},
{"id":235,"label":"359 Gina Point","description":"Lallayug","country":"Philippines"},
{"id":236,"label":"1147 Everett Alley","description":"Debrecen","country":"Hungary"},
{"id":237,"label":"8937 Jana Place","description":"Jambesari","country":"Indonesia"},
{"id":238,"label":"97986 Hintze Crossing","description":"Pedro Betancourt","country":"Cuba"},
{"id":239,"label":"6513 Lakewood Gardens Way","description":"Ilaya","country":"Philippines"},
{"id":240,"label":"9424 Northfield Alley","description":"Cifuentes","country":"Cuba"},
{"id":241,"label":"24708 Valley Edge Drive","description":"Valle de Guanape","country":"Venezuela"},
{"id":242,"label":"4852 American Way","description":"Cagmanaba","country":"Philippines"},
{"id":243,"label":"66212 Bunting Terrace","description":"Tallbīsah","country":"Syria"},
{"id":244,"label":"3 Merry Hill","description":"Bralin","country":"Poland"},
{"id":245,"label":"32 Veith Street","description":"Jianghong","country":"China"},
{"id":246,"label":"16 Sutteridge Terrace","description":"Pęczniew","country":"Poland"},
{"id":247,"label":"20 Village Green Point","description":"Stockholm","country":"Sweden"},
{"id":248,"label":"9 Clemons Road","description":"Bayan","country":"Indonesia"},
{"id":249,"label":"406 Tennessee Junction","description":"Belung Satu","country":"Indonesia"},
{"id":250,"label":"03 Transport Junction","description":"Zipaquirá","country":"Colombia"},
{"id":251,"label":"40 International Center","description":"Matagalpa","country":"Nicaragua"},
{"id":252,"label":"4 Stephen Place","description":"Banjarbaru","country":"Indonesia"},
{"id":253,"label":"59 Mallory Parkway","description":"Cergy-Pontoise","country":"France"},
{"id":254,"label":"38 Bowman Junction","description":"Honghai","country":"China"},
{"id":255,"label":"587 Ludington Lane","description":"Machico","country":"Portugal"},
{"id":256,"label":"9613 Mesta Plaza","description":"Jāti","country":"Pakistan"},
{"id":257,"label":"0 Fisk Lane","description":"Quzhou","country":"China"},
{"id":258,"label":"98830 Sutherland Road","description":"Calamba","country":"Philippines"},
{"id":259,"label":"37 Birchwood Place","description":"Sumbermanggis","country":"Indonesia"},
{"id":260,"label":"665 Onsgard Circle","description":"Bhokadoke","country":"Indonesia"},
{"id":261,"label":"1947 Cody Alley","description":"Wenquan","country":"China"},
{"id":262,"label":"88517 Pleasure Terrace","description":"El Estor","country":"Guatemala"},
{"id":263,"label":"62 Petterle Alley","description":"Krajan","country":"Indonesia"},
{"id":264,"label":"58 Basil Trail","description":"Okanagan","country":"Canada"},
{"id":265,"label":"20 Doe Crossing Alley","description":"Suna","country":"Russia"},
{"id":266,"label":"76 Sunnyside Trail","description":"Telangi Satu","country":"Indonesia"},
{"id":267,"label":"2303 Moland Parkway","description":"Patrocinio","country":"Philippines"},
{"id":268,"label":"1 Colorado Trail","description":"Aliwal North","country":"South Africa"},
{"id":269,"label":"11522 Gale Way","description":"Ketapang","country":"Indonesia"},
{"id":270,"label":"79250 Anniversary Circle","description":"Xincheng","country":"China"},
{"id":271,"label":"4684 Farmco Street","description":"Berehomet","country":"Ukraine"},
{"id":272,"label":"266 Fisk Lane","description":"Oton","country":"Philippines"},
{"id":273,"label":"3984 Forster Plaza","description":"Le Pontet","country":"France"},
{"id":274,"label":"4136 Carioca Alley","description":"Bologna","country":"Italy"},
{"id":275,"label":"6 Manley Way","description":"Nong Chik","country":"Thailand"},
{"id":276,"label":"0655 Pearson Trail","description":"Ngori","country":"Indonesia"},
{"id":277,"label":"9440 Blaine Junction","description":"Nurota Shahri","country":"Uzbekistan"},
{"id":278,"label":"498 Pawling Street","description":"Leyuan","country":"China"},
{"id":279,"label":"542 Summer Ridge Place","description":"Jiexiu","country":"China"},
{"id":280,"label":"1511 Little Fleur Point","description":"Yunmeng Chengguanzhen","country":"China"},
{"id":281,"label":"07079 Annamark Trail","description":"Fenyan","country":"China"},
{"id":282,"label":"4573 Dexter Lane","description":"Augusto Corrêa","country":"Brazil"},
{"id":283,"label":"63062 Mandrake Parkway","description":"Bajiao","country":"China"},
{"id":284,"label":"25 Truax Pass","description":"Lihu","country":"China"},
{"id":285,"label":"82 Novick Drive","description":"Bardiyā","country":"Nepal"},
{"id":286,"label":"9846 Forest Run Parkway","description":"‘Alīābād-e Katūl","country":"Iran"},
{"id":287,"label":"893 Bartillon Parkway","description":"Mount Pearl","country":"Canada"},
{"id":288,"label":"287 Weeping Birch Drive","description":"Manila","country":"Philippines"},
{"id":289,"label":"639 Hudson Way","description":"Hulan","country":"China"},
{"id":290,"label":"89 Hazelcrest Point","description":"Mitry-Mory","country":"France"},
{"id":291,"label":"5021 Bay Terrace","description":"Levallois-Perret","country":"France"},
{"id":292,"label":"1 Jenna Hill","description":"Chongqing","country":"China"},
{"id":293,"label":"47 Montana Parkway","description":"Nazaré da Mata","country":"Brazil"},
{"id":294,"label":"9 Kedzie Drive","description":"Laveiras","country":"Portugal"},
{"id":295,"label":"6 Dryden Lane","description":"Philadelphia","country":"United States"},
{"id":296,"label":"1 Debs Crossing","description":"Łaziska Górne","country":"Poland"},
{"id":297,"label":"879 Sugar Junction","description":"Pristina","country":"Kosovo"},
{"id":298,"label":"901 Dayton Street","description":"Hošťka","country":"Czech Republic"},
{"id":299,"label":"6 Montana Pass","description":"Daqiao","country":"China"},
{"id":300,"label":"836 Shopko Junction","description":"Bugo","country":"Philippines"},
{"id":301,"label":"1 Tony Trail","description":"Villa Carlos Paz","country":"Argentina"},
{"id":302,"label":"81243 Gerald Drive","description":"Si Mahosot","country":"Thailand"},
{"id":303,"label":"04 Loomis Hill","description":"Alicia","country":"Philippines"},
{"id":304,"label":"08 Westport Alley","description":"Petrivka","country":"Ukraine"},
{"id":305,"label":"31574 Pine View Center","description":"Anjihai","country":"China"},
{"id":306,"label":"83 Coleman Street","description":"Tual","country":"Indonesia"},
{"id":307,"label":"29 Dixon Parkway","description":"Penebel","country":"Indonesia"},
{"id":308,"label":"174 Messerschmidt Junction","description":"Potęgowo","country":"Poland"},
{"id":309,"label":"2307 Westport Center","description":"Orangeville","country":"Canada"},
{"id":310,"label":"0 Monument Place","description":"Mahe","country":"China"},
{"id":311,"label":"98 Sage Drive","description":"Narail","country":"Bangladesh"},
{"id":312,"label":"6 Loomis Terrace","description":"Haiyang","country":"China"},
{"id":313,"label":"43427 Marquette Hill","description":"Pingfeng","country":"China"},
{"id":314,"label":"5 Elgar Plaza","description":"Ciudad Ojeda","country":"Venezuela"},
{"id":315,"label":"55 Toban Parkway","description":"Seleuš","country":"Serbia"},
{"id":316,"label":"93 Duke Park","description":"Norrköping","country":"Sweden"},
{"id":317,"label":"27 Pawling Terrace","description":"Buinsk","country":"Russia"},
{"id":318,"label":"561 Schurz Point","description":"Yugang","country":"China"},
{"id":319,"label":"41980 Golf Park","description":"Huai Yot","country":"Thailand"},
{"id":320,"label":"5 Rockefeller Lane","description":"Tangba","country":"China"},
{"id":321,"label":"87262 Homewood Center","description":"Kosum Phisai","country":"Thailand"},
{"id":322,"label":"667 Del Sol Crossing","description":"Bayasgalant","country":"Mongolia"},
{"id":323,"label":"83 Duke Trail","description":"Welkom","country":"South Africa"},
{"id":324,"label":"16631 Hovde Avenue","description":"Jeziorzany","country":"Poland"},
{"id":325,"label":"34 Blaine Point","description":"Cuenca","country":"Ecuador"},
{"id":326,"label":"8 Lien Street","description":"Kembangarum","country":"Indonesia"},
{"id":327,"label":"86625 Kenwood Parkway","description":"Montgomery","country":"United States"},
{"id":328,"label":"11 Prairieview Road","description":"Tikhvin","country":"Russia"},
{"id":329,"label":"0312 Dawn Trail","description":"Guhuai","country":"China"},
{"id":330,"label":"85810 Hooker Park","description":"Ogoja","country":"Nigeria"},
{"id":331,"label":"652 Meadow Ridge Plaza","description":"Bārkhān","country":"Pakistan"},
{"id":332,"label":"899 Butternut Place","description":"Outokumpu","country":"Finland"},
{"id":333,"label":"1958 Vernon Street","description":"Sovetskiy","country":"Russia"},
{"id":334,"label":"09 Scofield Parkway","description":"Shuhong","country":"China"},
{"id":335,"label":"915 Steensland Plaza","description":"Norrköping","country":"Sweden"},
{"id":336,"label":"76 Onsgard Street","description":"Länsi-Turunmaa","country":"Finland"},
{"id":337,"label":"0 Buell Pass","description":"Petersfield","country":"Jamaica"},
{"id":338,"label":"7 Vernon Circle","description":"Beixiaoying","country":"China"},
{"id":339,"label":"8143 Glendale Plaza","description":"Pucallpa","country":"Peru"},
{"id":340,"label":"253 Eagle Crest Circle","description":"Nubma","country":"China"},
{"id":341,"label":"585 Spenser Terrace","description":"Haquira","country":"Peru"},
{"id":342,"label":"3476 Dexter Place","description":"Jalinan","country":"Indonesia"},
{"id":343,"label":"1 Dexter Circle","description":"Utarapasar","country":"Indonesia"},
{"id":344,"label":"111 Lotheville Place","description":"Dongda","country":"China"},
{"id":345,"label":"9662 Clyde Gallagher Pass","description":"Pitogo","country":"Philippines"},
{"id":346,"label":"3 Warrior Road","description":"Destrnik","country":"Slovenia"},
{"id":347,"label":"03 Kings Terrace","description":"Čajniče","country":"Bosnia and Herzegovina"},
{"id":348,"label":"209 Crest Line Lane","description":"Menanga","country":"Indonesia"},
{"id":349,"label":"8 7th Alley","description":"Dalang","country":"China"},
{"id":350,"label":"011 Hollow Ridge Parkway","description":"Chaoyangdong","country":"China"},
{"id":351,"label":"72190 Everett Junction","description":"Pomerode","country":"Brazil"},
{"id":352,"label":"8 Maple Court","description":"Pilang","country":"Indonesia"},
{"id":353,"label":"215 Bluestem Road","description":"Na Muen","country":"Thailand"},
{"id":354,"label":"6 Troy Parkway","description":"Pýli","country":"Greece"},
{"id":355,"label":"530 Utah Pass","description":"Jose Maria Morelos","country":"Mexico"},
{"id":356,"label":"85 Havey Way","description":"Papringan","country":"Indonesia"},
{"id":357,"label":"43573 Troy Road","description":"Laikit, Laikit II (Dimembe)","country":"Indonesia"},
{"id":358,"label":"010 Thackeray Center","description":"Xinlong","country":"China"},
{"id":359,"label":"70 Elgar Parkway","description":"Laidian","country":"China"},
{"id":360,"label":"2 Hoard Crossing","description":"Kedungbacin","country":"Indonesia"},
{"id":361,"label":"52218 Clove Hill","description":"Columbia","country":"United States"},
{"id":362,"label":"6030 Old Shore Pass","description":"Kumagunnam","country":"Nigeria"},
{"id":363,"label":"94 Forest Court","description":"Tayum","country":"Philippines"},
{"id":364,"label":"72 Sachtjen Way","description":"Valleymount","country":"Ireland"},
{"id":365,"label":"40 Monica Pass","description":"Rubizhne","country":"Ukraine"},
{"id":366,"label":"0 Brown Avenue","description":"Rio Novo do Sul","country":"Brazil"},
{"id":367,"label":"6 Ridgeview Drive","description":"Túquerres","country":"Colombia"},
{"id":368,"label":"214 Kenwood Plaza","description":"Sezures","country":"Portugal"},
{"id":369,"label":"3 Judy Hill","description":"Fengmen","country":"China"},
{"id":370,"label":"01975 Michigan Junction","description":"Choropampa","country":"Peru"},
{"id":371,"label":"8097 Buell Road","description":"Konga","country":"Indonesia"},
{"id":372,"label":"7 Vahlen Pass","description":"Dār Kulayb","country":"Bahrain"},
{"id":373,"label":"203 Lunder Road","description":"Grand Junction","country":"United States"},
{"id":374,"label":"88345 Kinsman Point","description":"Kināna","country":"Sudan"},
{"id":375,"label":"0 High Crossing Parkway","description":"Hushaat","country":"Mongolia"},
{"id":376,"label":"9 Myrtle Pass","description":"Qiulu","country":"China"},
{"id":377,"label":"9 Stuart Road","description":"Sulmierzyce","country":"Poland"},
{"id":378,"label":"8844 Mcbride Hill","description":"Fort Lauderdale","country":"United States"},
{"id":379,"label":"81 Susan Way","description":"Neepawa","country":"Canada"},
{"id":380,"label":"3605 Charing Cross Drive","description":"Lochovice","country":"Czech Republic"},
{"id":381,"label":"0578 Toban Terrace","description":"Inuotose","country":"Japan"},
{"id":382,"label":"92 Vera Court","description":"Kanzaki","country":"Japan"},
{"id":383,"label":"81632 Charing Cross Pass","description":"Al Bawīţī","country":"Egypt"},
{"id":384,"label":"2332 Sunbrook Plaza","description":"Saint-Quentin","country":"France"},
{"id":385,"label":"4804 Tennyson Circle","description":"Rancaranji","country":"Indonesia"},
{"id":386,"label":"75 Gale Terrace","description":"Thủ Thừa","country":"Vietnam"},
{"id":387,"label":"4902 Forest Dale Park","description":"Vanderbijlpark","country":"South Africa"},
{"id":388,"label":"6269 Hansons Alley","description":"Murillo","country":"Colombia"},
{"id":389,"label":"94712 Eggendart Alley","description":"Noisy-le-Grand","country":"France"},
{"id":390,"label":"0 Hayes Center","description":"Zaslawye","country":"Belarus"},
{"id":391,"label":"3939 Mesta Street","description":"Sorinomo","country":"Indonesia"},
{"id":392,"label":"09493 Miller Drive","description":"Georgīevka","country":"Kazakhstan"},
{"id":393,"label":"5101 Farragut Lane","description":"Bollstabruk","country":"Sweden"},
{"id":394,"label":"381 Algoma Pass","description":"Pateros","country":"Philippines"},
{"id":395,"label":"65758 Waubesa Hill","description":"Fuming","country":"China"},
{"id":396,"label":"5933 Commercial Circle","description":"Presidente Prudente","country":"Brazil"},
{"id":397,"label":"40 Nova Street","description":"Carriedo","country":"Philippines"},
{"id":398,"label":"1 Sachtjen Drive","description":"Granja do Tedo","country":"Portugal"},
{"id":399,"label":"82 Golf Course Circle","description":"Jagna","country":"Philippines"},
{"id":400,"label":"6569 Little Fleur Trail","description":"Cirumput","country":"Indonesia"},
{"id":401,"label":"72321 Trailsway Street","description":"Gora","country":"Nigeria"},
{"id":402,"label":"93 Clove Place","description":"Jabonga","country":"Philippines"},
{"id":403,"label":"4 Veith Lane","description":"Deventer","country":"Netherlands"},
{"id":404,"label":"10 Judy Center","description":"Changpo","country":"China"},
{"id":405,"label":"03 Kings Place","description":"Mwene-Ditu","country":"Democratic Republic of the Congo"},
{"id":406,"label":"5 Doe Crossing Alley","description":"Harrison Brook","country":"Canada"},
{"id":407,"label":"5256 5th Court","description":"Caçapava","country":"Brazil"},
{"id":408,"label":"789 Oak Way","description":"Karagay","country":"Russia"},
{"id":409,"label":"0205 Northport Street","description":"Wleń","country":"Poland"},
{"id":410,"label":"168 Graceland Drive","description":"La Estancia","country":"Honduras"},
{"id":411,"label":"51678 Loeprich Pass","description":"Independencia","country":"Peru"},
{"id":412,"label":"2426 Onsgard Plaza","description":"Empório","country":"Greece"},
{"id":413,"label":"829 Oriole Drive","description":"Veiga","country":"Portugal"},
{"id":414,"label":"51 Lakewood Parkway","description":"Seredyna-Buda","country":"Ukraine"},
{"id":415,"label":"66 Nelson Parkway","description":"Ḩammām Wāşil","country":"Syria"},
{"id":416,"label":"1494 Blackbird Hill","description":"Gaojian","country":"China"},
{"id":417,"label":"7430 Fairfield Point","description":"Jiaotang","country":"China"},
{"id":418,"label":"58 Sloan Circle","description":"Cane","country":"Honduras"},
{"id":419,"label":"965 Mayfield Court","description":"Retorta","country":"Portugal"},
{"id":420,"label":"613 Boyd Alley","description":"Caromatan","country":"Philippines"},
{"id":421,"label":"0312 Anderson Hill","description":"Tadou","country":"China"},
{"id":422,"label":"40721 Hanson Parkway","description":"Muyinga","country":"Burundi"},
{"id":423,"label":"50 Swallow Junction","description":"Borova","country":"Ukraine"},
{"id":424,"label":"91 Rigney Crossing","description":"Xiagong","country":"China"},
{"id":425,"label":"8 Anthes Park","description":"Yishan","country":"China"},
{"id":426,"label":"1346 Montana Park","description":"Firmat","country":"Argentina"},
{"id":427,"label":"250 Ilene Place","description":"Huangqi","country":"China"},
{"id":428,"label":"76 Fordem Drive","description":"Honghualiangzi","country":"China"},
{"id":429,"label":"4 Fremont Center","description":"Harrisburg","country":"United States"},
{"id":430,"label":"6612 Farwell Point","description":"Luxor","country":"Egypt"},
{"id":431,"label":"55197 Pleasure Plaza","description":"Saray","country":"Azerbaijan"},
{"id":432,"label":"8 Lakewood Gardens Pass","description":"Vovchans’k","country":"Ukraine"},
{"id":433,"label":"755 Delaware Street","description":"Ocongate","country":"Peru"},
{"id":434,"label":"89 Marcy Street","description":"Skorogoszcz","country":"Poland"},
{"id":435,"label":"397 Buell Way","description":"Vallentuna","country":"Sweden"},
{"id":436,"label":"5804 Bunker Hill Hill","description":"Chaviña","country":"Peru"},
{"id":437,"label":"25562 Sheridan Trail","description":"Bayt Liqyā","country":"Palestinian Territory"},
{"id":438,"label":"72766 Corscot Point","description":"Kulunda","country":"Russia"},
{"id":439,"label":"8 Bultman Parkway","description":"Kurów","country":"Poland"},
{"id":440,"label":"861 Knutson Lane","description":"Chexi","country":"China"},
{"id":441,"label":"94 Anthes Circle","description":"Wangkung","country":"Indonesia"},
{"id":442,"label":"1269 Drewry Plaza","description":"Pagsañgahan","country":"Philippines"},
{"id":443,"label":"6 Magdeline Point","description":"Tais","country":"Indonesia"},
{"id":444,"label":"6 Calypso Court","description":"København","country":"Denmark"},
{"id":445,"label":"98790 Hovde Circle","description":"Lepanto","country":"Philippines"},
{"id":446,"label":"30 High Crossing Junction","description":"Yatsushiro","country":"Japan"},
{"id":447,"label":"609 Village Green Center","description":"Cherepovets","country":"Russia"},
{"id":448,"label":"689 Mockingbird Point","description":"Huachos","country":"Peru"},
{"id":449,"label":"60602 Delladonna Place","description":"Niamey","country":"Niger"},
{"id":450,"label":"0188 Mandrake Pass","description":"Byera Village","country":"Saint Vincent and the Grenadines"},
{"id":451,"label":"90 Aberg Lane","description":"Yongfeng","country":"China"},
{"id":452,"label":"79740 Vahlen Center","description":"Bantarpanjang","country":"Indonesia"},
{"id":453,"label":"338 Derek Crossing","description":"Kasreman","country":"Indonesia"},
{"id":454,"label":"663 Duke Center","description":"Nozdrzec","country":"Poland"},
{"id":455,"label":"55 Scott Plaza","description":"Soreang","country":"Indonesia"},
{"id":456,"label":"496 David Circle","description":"Junzhuang","country":"China"},
{"id":457,"label":"68612 Lakeland Plaza","description":"Hualingang","country":"China"},
{"id":458,"label":"63 Vidon Center","description":"Bayang","country":"China"},
{"id":459,"label":"25 Helena Pass","description":"Louveira","country":"Brazil"},
{"id":460,"label":"2863 Barby Alley","description":"Pogag","country":"Indonesia"},
{"id":461,"label":"37529 Paget Crossing","description":"Działdowo","country":"Poland"},
{"id":462,"label":"540 Melrose Trail","description":"Bailiang","country":"China"},
{"id":463,"label":"0 Randy Circle","description":"Macachín","country":"Argentina"},
{"id":464,"label":"90590 Eggendart Court","description":"Chenjiahe","country":"China"},
{"id":465,"label":"8 Clove Drive","description":"Aviles","country":"Spain"},
{"id":466,"label":"1164 Continental Drive","description":"Tapacocha","country":"Peru"},
{"id":467,"label":"8010 Basil Plaza","description":"Yong’an","country":"China"},
{"id":468,"label":"80930 Rigney Junction","description":"Cibodas","country":"Indonesia"},
{"id":469,"label":"065 Canary Street","description":"Sovetskoye","country":"Russia"},
{"id":470,"label":"612 Grover Plaza","description":"Aucayacu","country":"Peru"},
{"id":471,"label":"6 Weeping Birch Terrace","description":"Choya","country":"Russia"},
{"id":472,"label":"2 Roth Avenue","description":"Catarina","country":"Nicaragua"},
{"id":473,"label":"02 Judy Lane","description":"Batibati","country":"Indonesia"},
{"id":474,"label":"3463 Colorado Point","description":"Cahul","country":"Moldova"},
{"id":475,"label":"41758 Annamark Pass","description":"Lepanto","country":"Philippines"},
{"id":476,"label":"21037 Cordelia Avenue","description":"Gaya","country":"Niger"},
{"id":477,"label":"265 Truax Parkway","description":"Kinamayan","country":"Philippines"},
{"id":478,"label":"95873 Porter Place","description":"Tajao","country":"Philippines"},
{"id":479,"label":"00209 Lerdahl Center","description":"Nanterre","country":"France"},
{"id":480,"label":"62 Sherman Place","description":"Kandy","country":"Sri Lanka"},
{"id":481,"label":"42 Tennessee Terrace","description":"Planaltina","country":"Brazil"},
{"id":482,"label":"3099 Arizona Terrace","description":"Laxou","country":"France"},
{"id":483,"label":"59 Blackbird Avenue","description":"New-Richmond","country":"Canada"},
{"id":484,"label":"95 Nobel Point","description":"Yashio-shi","country":"Japan"},
{"id":485,"label":"7683 Independence Lane","description":"São Francisco do Conde","country":"Brazil"},
{"id":486,"label":"1 Becker Road","description":"San Jorge","country":"Argentina"},
{"id":487,"label":"43 Sommers Way","description":"Guilmaro","country":"Benin"},
{"id":488,"label":"6 Crescent Oaks Parkway","description":"Hashtgerd","country":"Iran"},
{"id":489,"label":"77 Marquette Drive","description":"Labuan","country":"Malaysia"},
{"id":490,"label":"0398 Sunbrook Pass","description":"Pergamino","country":"Argentina"},
{"id":491,"label":"926 Thompson Place","description":"Wuxihe","country":"China"},
{"id":492,"label":"043 Reinke Plaza","description":"Pochuta","country":"Guatemala"},
{"id":493,"label":"08 Raven Hill","description":"Mahikeng","country":"South Africa"},
{"id":494,"label":"89143 Holy Cross Avenue","description":"Carleton-sur-Mer","country":"Canada"},
{"id":495,"label":"6 Manley Trail","description":"Oshawa","country":"Canada"},
{"id":496,"label":"4 Delaware Crossing","description":"Oslo","country":"Norway"},
{"id":497,"label":"3762 Scofield Way","description":"Konakridee","country":"Sierra Leone"},
{"id":498,"label":"23219 Hanover Drive","description":"Ufa","country":"Russia"},
{"id":499,"label":"81 Elka Avenue","description":"San Francisco","country":"Mexico"},
{"id":500,"label":"011 Hanson Plaza","description":"Caucagüito","country":"Venezuela"},
{"id":501,"label":"2963 Mockingbird Way","description":"Wangzuizi","country":"China"},
{"id":502,"label":"323 Bonner Road","description":"Persen","country":"Indonesia"},
{"id":503,"label":"50 Sage Drive","description":"Rumoi","country":"Japan"},
{"id":504,"label":"31 Morning Trail","description":"Xibin","country":"China"},
{"id":505,"label":"4896 Bartelt Crossing","description":"Chahe","country":"China"},
{"id":506,"label":"06 Parkside Alley","description":"Vacaria","country":"Brazil"},
{"id":507,"label":"9 Petterle Hill","description":"Les Sables-d'Olonne","country":"France"},
{"id":508,"label":"9286 Forest Run Alley","description":"Nogoonnuur","country":"Mongolia"},
{"id":509,"label":"9 Lindbergh Terrace","description":"Sobeok","country":"Indonesia"},
{"id":510,"label":"41131 Park Meadow Plaza","description":"Marugame","country":"Japan"},
{"id":511,"label":"23 Fisk Way","description":"Guozhuang","country":"China"},
{"id":512,"label":"931 Briar Crest Center","description":"New Agutaya","country":"Philippines"},
{"id":513,"label":"5351 Pond Hill","description":"Ust’-Kut","country":"Russia"},
{"id":514,"label":"279 Kipling Park","description":"Cayambe","country":"Ecuador"},
{"id":515,"label":"6564 Lighthouse Bay Hill","description":"Baiyun","country":"China"},
{"id":516,"label":"45929 Mcguire Lane","description":"Carleton-sur-Mer","country":"Canada"},
{"id":517,"label":"2483 Green Ridge Plaza","description":"Nové Město nad Metují","country":"Czech Republic"},
{"id":518,"label":"4 Dorton Plaza","description":"Saint-Jérôme","country":"Canada"},
{"id":519,"label":"0 Florence Junction","description":"Pilchowice","country":"Poland"},
{"id":520,"label":"49031 Claremont Point","description":"San Diego","country":"Philippines"},
{"id":521,"label":"632 Crowley Alley","description":"Oxelösund","country":"Sweden"},
{"id":522,"label":"12688 Cordelia Trail","description":"Mislīyah","country":"Palestinian Territory"},
{"id":523,"label":"8 Mifflin Point","description":"Yandian","country":"China"},
{"id":524,"label":"277 Bartelt Way","description":"Belisario Dominguez","country":"Mexico"},
{"id":525,"label":"4851 Fair Oaks Place","description":"Frederiksberg","country":"Denmark"},
{"id":526,"label":"396 Londonderry Park","description":"Sheli","country":"China"},
{"id":527,"label":"9488 Golf View Road","description":"Santa Rita","country":"Venezuela"},
{"id":528,"label":"90 Maple Drive","description":"Sölvesborg","country":"Sweden"},
{"id":529,"label":"922 Larry Trail","description":"Proletar","country":"Tajikistan"},
{"id":530,"label":"09 Raven Terrace","description":"Jalanbaru","country":"Indonesia"},
{"id":531,"label":"4 Sheridan Terrace","description":"Wutong","country":"China"},
{"id":532,"label":"00408 Cardinal Pass","description":"Rājo Khanāni","country":"Pakistan"},
{"id":533,"label":"8596 Cherokee Place","description":"Haysyn","country":"Ukraine"},
{"id":534,"label":"3 Bonner Trail","description":"Yanggang","country":"China"},
{"id":535,"label":"02 Aberg Way","description":"Novi Kneževac","country":"Serbia"},
{"id":536,"label":"02 Spaight Pass","description":"Ancasti","country":"Argentina"},
{"id":537,"label":"20975 Melrose Parkway","description":"Lumbatan","country":"Philippines"},
{"id":538,"label":"26406 Briar Crest Pass","description":"Luna","country":"Philippines"},
{"id":539,"label":"16916 Oakridge Road","description":"les Escaldes","country":"Andorra"},
{"id":540,"label":"22 Wayridge Junction","description":"Panitian","country":"Philippines"},
{"id":541,"label":"1891 Eagan Court","description":"Kremenki","country":"Russia"},
{"id":542,"label":"9669 Commercial Place","description":"Osias","country":"Philippines"},
{"id":543,"label":"201 Dottie Road","description":"San Miguel","country":"Philippines"},
{"id":544,"label":"9 Scofield Park","description":"Chengkan","country":"China"},
{"id":545,"label":"3 Debra Avenue","description":"Sanxi","country":"China"},
{"id":546,"label":"69 Fulton Pass","description":"Shiyuan","country":"China"},
{"id":547,"label":"88 Ramsey Lane","description":"Yanguan","country":"China"},
{"id":548,"label":"1732 Boyd Way","description":"Banqiao","country":"China"},
{"id":549,"label":"581 Upham Crossing","description":"Pulo","country":"Philippines"},
{"id":550,"label":"7857 Bartelt Trail","description":"Sokol’skoye","country":"Russia"},
{"id":551,"label":"890 Homewood Circle","description":"Lokavec","country":"Slovenia"},
{"id":552,"label":"7266 North Lane","description":"Valença do Douro","country":"Portugal"},
{"id":553,"label":"418 Jay Alley","description":"Pombal","country":"Brazil"},
{"id":554,"label":"6 Norway Maple Lane","description":"Somovo","country":"Russia"},
{"id":555,"label":"4482 Dryden Hill","description":"Güines","country":"Cuba"},
{"id":556,"label":"3372 Butterfield Road","description":"Cabreúva","country":"Brazil"},
{"id":557,"label":"62 Cordelia Street","description":"Kota Kinabalu","country":"Malaysia"},
{"id":558,"label":"2013 Loftsgordon Way","description":"Koppies","country":"South Africa"},
{"id":559,"label":"3502 7th Street","description":"Zhoutian","country":"China"},
{"id":560,"label":"335 Brickson Park Street","description":"Penhold","country":"Canada"},
{"id":561,"label":"1674 Alpine Street","description":"Montbéliard","country":"France"},
{"id":562,"label":"0054 Nelson Lane","description":"Huadi","country":"China"},
{"id":563,"label":"30342 Valley Edge Court","description":"Bayan Qagan","country":"China"},
{"id":564,"label":"77 Oxford Junction","description":"Józefów","country":"Poland"},
{"id":565,"label":"530 Killdeer Point","description":"Estaca","country":"Philippines"},
{"id":566,"label":"73 Quincy Parkway","description":"Heby","country":"Sweden"},
{"id":567,"label":"84208 Toban Place","description":"Cihurip Satu","country":"Indonesia"},
{"id":568,"label":"19 Doe Crossing Place","description":"Xinzheng","country":"China"},
{"id":569,"label":"6 Brentwood Lane","description":"Dikou","country":"China"},
{"id":570,"label":"581 Sutherland Parkway","description":"Cabannungan Second","country":"Philippines"},
{"id":571,"label":"28 Waywood Plaza","description":"Nigríta","country":"Greece"},
{"id":572,"label":"10 Ryan Plaza","description":"Berlin","country":"Germany"},
{"id":573,"label":"96823 4th Road","description":"Jiangshan","country":"China"},
{"id":574,"label":"581 Dapin Lane","description":"Qionghai","country":"China"},
{"id":575,"label":"4449 East Place","description":"Uluale","country":"Indonesia"},
{"id":576,"label":"516 Ridge Oak Point","description":"Arias","country":"Argentina"},
{"id":577,"label":"77 Hoard Center","description":"Velyka Mykhaylivka","country":"Ukraine"},
{"id":578,"label":"0834 Bay Terrace","description":"Anaco","country":"Venezuela"},
{"id":579,"label":"9359 Main Plaza","description":"Waru","country":"Indonesia"},
{"id":580,"label":"71021 Pearson Parkway","description":"Anávra","country":"Greece"},
{"id":581,"label":"663 8th Crossing","description":"Pingyin","country":"China"},
{"id":582,"label":"08633 Kensington Point","description":"Hyesan-si","country":"North Korea"},
{"id":583,"label":"419 Bunting Alley","description":"Ilembula","country":"Tanzania"},
{"id":584,"label":"02680 Riverside Parkway","description":"Colmeal","country":"Portugal"},
{"id":585,"label":"0361 Towne Drive","description":"Askim","country":"Norway"},
{"id":586,"label":"5627 Valley Edge Circle","description":"Correia Pinto","country":"Brazil"},
{"id":587,"label":"7 Shelley Plaza","description":"Kepahiang","country":"Indonesia"},
{"id":588,"label":"761 Lukken Drive","description":"Adare","country":"Ireland"},
{"id":589,"label":"773 Warrior Parkway","description":"Sasnovy Bor","country":"Belarus"},
{"id":590,"label":"243 Bartelt Center","description":"Mouzourás","country":"Greece"},
{"id":591,"label":"87 Mcguire Plaza","description":"Napierville","country":"Canada"},
{"id":592,"label":"552 Rieder Point","description":"Mosteiros","country":"Portugal"},
{"id":593,"label":"261 Meadow Ridge Road","description":"Edinburgh of the Seven Seas","country":"Saint Helena"},
{"id":594,"label":"8 Veith Parkway","description":"Brusyliv","country":"Ukraine"},
{"id":595,"label":"77535 Shasta Center","description":"Heshang","country":"China"},
{"id":596,"label":"66399 Iowa Crossing","description":"Mentoro Wetan","country":"Indonesia"},
{"id":597,"label":"173 Prairieview Parkway","description":"Dourbali","country":"Chad"},
{"id":598,"label":"8 Marquette Alley","description":"Santo Domingo","country":"Dominican Republic"},
{"id":599,"label":"725 Macpherson Lane","description":"Dadiya","country":"Nigeria"},
{"id":600,"label":"6 Warbler Junction","description":"Libog","country":"Philippines"},
{"id":601,"label":"50 Katie Way","description":"Kireyevsk","country":"Russia"},
{"id":602,"label":"08 Paget Center","description":"Prengtale","country":"Indonesia"},
{"id":603,"label":"938 Maple Wood Alley","description":"Norberg","country":"Sweden"},
{"id":604,"label":"207 Crest Line Point","description":"Metsemotlhaba","country":"Botswana"},
{"id":605,"label":"5677 Maple Wood Drive","description":"Poljčane","country":"Slovenia"},
{"id":606,"label":"163 Loftsgordon Street","description":"Qitan","country":"China"},
{"id":607,"label":"811 Dawn Alley","description":"Aix-en-Provence","country":"France"},
{"id":608,"label":"3583 Westerfield Crossing","description":"Samamiya","country":"Nigeria"},
{"id":609,"label":"62510 Schmedeman Pass","description":"Limbuhan","country":"Philippines"},
{"id":610,"label":"2482 Blue Bill Park Street","description":"Xinghuo","country":"China"},
{"id":611,"label":"74946 Hermina Drive","description":"Semuda","country":"Indonesia"},
{"id":612,"label":"843 Katie Lane","description":"Moinhos","country":"Portugal"},
{"id":613,"label":"6884 Center Park","description":"Örebro","country":"Sweden"},
{"id":614,"label":"853 Arizona Junction","description":"Ishëm","country":"Albania"},
{"id":615,"label":"0319 Eliot Parkway","description":"Australia Square","country":"Australia"},
{"id":616,"label":"9254 Moulton Way","description":"Kromasan","country":"Indonesia"},
{"id":617,"label":"2915 Merry Place","description":"Kokofata","country":"Mali"},
{"id":618,"label":"68 Glacier Hill Avenue","description":"Girona","country":"Spain"},
{"id":619,"label":"363 Farmco Center","description":"Pemba","country":"Mozambique"},
{"id":620,"label":"7 Carey Junction","description":"Heka","country":"China"},
{"id":621,"label":"9 Carpenter Court","description":"Barra do Bugres","country":"Brazil"},
{"id":622,"label":"40 Main Place","description":"Kopashnovo","country":"Ukraine"},
{"id":623,"label":"9010 Valley Edge Pass","description":"København","country":"Denmark"},
{"id":624,"label":"47 Muir Crossing","description":"Big Bend","country":"Swaziland"},
{"id":625,"label":"86981 Linden Place","description":"Zhemtala","country":"Russia"},
{"id":626,"label":"18040 Sloan Street","description":"Bartsrashen","country":"Armenia"},
{"id":627,"label":"1626 Hintze Plaza","description":"Miliangju","country":"China"},
{"id":628,"label":"74 Waxwing Crossing","description":"Akzhal","country":"Kazakhstan"},
{"id":629,"label":"31360 Rieder Alley","description":"Liancheng","country":"China"},
{"id":630,"label":"2250 Basil Street","description":"Santa Cruz","country":"Portugal"},
{"id":631,"label":"982 Crescent Oaks Court","description":"Meedhoo","country":"Maldives"},
{"id":632,"label":"078 Dakota Avenue","description":"Kitamilo","country":"Uganda"},
{"id":633,"label":"351 Iowa Center","description":"Kasimov","country":"Russia"},
{"id":634,"label":"3035 Talmadge Circle","description":"Portão","country":"Brazil"},
{"id":635,"label":"59697 John Wall Point","description":"Morden","country":"Canada"},
{"id":636,"label":"905 Walton Circle","description":"Benito Juarez","country":"Mexico"},
{"id":637,"label":"5840 Lakeland Hill","description":"Babagan","country":"Indonesia"},
{"id":638,"label":"9 Bonner Lane","description":"Jurak Lao’","country":"Indonesia"},
{"id":639,"label":"26369 Moulton Pass","description":"Huangben","country":"China"},
{"id":640,"label":"039 Golf Court","description":"Khānpur","country":"Pakistan"},
{"id":641,"label":"32654 Golf View Trail","description":"Debre Mark’os","country":"Ethiopia"},
{"id":642,"label":"77 Sloan Way","description":"Tabatinga","country":"Brazil"},
{"id":643,"label":"775 Elgar Plaza","description":"Tieba","country":"China"},
{"id":644,"label":"8027 Raven Alley","description":"Mbigou","country":"Gabon"},
{"id":645,"label":"8431 La Follette Plaza","description":"St. Catharines","country":"Canada"},
{"id":646,"label":"189 Mallory Avenue","description":"San Pedro","country":"Belize"},
{"id":647,"label":"4 Maple Place","description":"Novoderevyankovskaya","country":"Russia"},
{"id":648,"label":"11 Loeprich Junction","description":"Dongfanghong","country":"China"},
{"id":649,"label":"3300 Hoepker Parkway","description":"Darungan","country":"Indonesia"},
{"id":650,"label":"39 Vahlen Drive","description":"Lidköping","country":"Sweden"},
{"id":651,"label":"858 Mendota Circle","description":"Al Jawādīyah","country":"Syria"},
{"id":652,"label":"8 Coleman Drive","description":"Maralal","country":"Kenya"},
{"id":653,"label":"7116 Florence Hill","description":"Xudat","country":"Azerbaijan"},
{"id":654,"label":"497 Leroy Way","description":"Mariestad","country":"Sweden"},
{"id":655,"label":"7951 Washington Crossing","description":"Kétou","country":"Benin"},
{"id":656,"label":"3 Duke Park","description":"Nipawin","country":"Canada"},
{"id":657,"label":"64 Merry Circle","description":"Merlo","country":"Argentina"},
{"id":658,"label":"71502 Farmco Avenue","description":"Boka","country":"Serbia"},
{"id":659,"label":"4856 Lighthouse Bay Court","description":"Gambalidio","country":"Philippines"},
{"id":660,"label":"4737 Lien Trail","description":"Wanga","country":"Indonesia"},
{"id":661,"label":"461 Pierstorff Terrace","description":"Vithkuq","country":"Albania"},
{"id":662,"label":"8 Caliangt Point","description":"Lindome","country":"Sweden"},
{"id":663,"label":"698 Division Way","description":"Dallas","country":"United States"},
{"id":664,"label":"168 Forest Dale Circle","description":"Jeju-si","country":"South Korea"},
{"id":665,"label":"807 Village Plaza","description":"Gwaram","country":"Nigeria"},
{"id":666,"label":"8 Stephen Center","description":"Sukamahi Satu","country":"Indonesia"},
{"id":667,"label":"9 Saint Paul Circle","description":"Tosno","country":"Russia"},
{"id":668,"label":"94731 Prairie Rose Avenue","description":"Maturín","country":"Venezuela"},
{"id":669,"label":"94 Longview Trail","description":"Muara Siberut","country":"Indonesia"},
{"id":670,"label":"4345 Graedel Plaza","description":"Penha","country":"Brazil"},
{"id":671,"label":"37306 Chive Trail","description":"Sovetskoye","country":"Russia"},
{"id":672,"label":"36 Heath Trail","description":"At-Bashi","country":"Kyrgyzstan"},
{"id":673,"label":"95050 Mariners Cove Court","description":"Călăraşi","country":"Moldova"},
{"id":674,"label":"52919 Nobel Alley","description":"Kishorganj","country":"Bangladesh"},
{"id":675,"label":"1 Blaine Avenue","description":"Korsze","country":"Poland"},
{"id":676,"label":"03080 Lyons Place","description":"Yessentukskaya","country":"Russia"},
{"id":677,"label":"48 Onsgard Hill","description":"Holice","country":"Czech Republic"},
{"id":678,"label":"67 New Castle Way","description":"Zbýšov","country":"Czech Republic"},
{"id":679,"label":"21551 Pearson Plaza","description":"Toyós","country":"Honduras"},
{"id":680,"label":"933 Northridge Hill","description":"Zhelin","country":"China"},
{"id":681,"label":"2 Sundown Road","description":"Shuihu","country":"China"},
{"id":682,"label":"9 Mcbride Place","description":"Lagangilang","country":"Philippines"},
{"id":683,"label":"97 Merry Court","description":"Phatthalung","country":"Thailand"},
{"id":684,"label":"7 Crownhardt Hill","description":"Huasahuasi","country":"Peru"},
{"id":685,"label":"0331 Sunnyside Circle","description":"Niverville","country":"Canada"},
{"id":686,"label":"70816 Loftsgordon Court","description":"Sakai","country":"Japan"},
{"id":687,"label":"2718 Armistice Way","description":"Bélabo","country":"Cameroon"},
{"id":688,"label":"076 Ronald Regan Park","description":"Maradabangga","country":"Indonesia"},
{"id":689,"label":"57437 Derek Lane","description":"Huanghai","country":"China"},
{"id":690,"label":"34555 Oxford Center","description":"Caobi","country":"China"},
{"id":691,"label":"44690 Autumn Leaf Point","description":"Lacolle","country":"Canada"},
{"id":692,"label":"806 Donald Crossing","description":"Sintansin","country":"South Korea"},
{"id":693,"label":"7 Bunker Hill Plaza","description":"Meadow Lake","country":"Canada"},
{"id":694,"label":"781 Mayfield Lane","description":"Na'ale","country":"Israel"},
{"id":695,"label":"32 Mccormick Avenue","description":"Dulian","country":"Philippines"},
{"id":696,"label":"34082 Darwin Park","description":"Himensulan","country":"Philippines"},
{"id":697,"label":"02 Springview Center","description":"Hallsberg","country":"Sweden"},
{"id":698,"label":"16 Beilfuss Alley","description":"Tol’yatti","country":"Russia"},
{"id":699,"label":"081 Union Lane","description":"Shpola","country":"Ukraine"},
{"id":700,"label":"425 Ridge Oak Circle","description":"Žeravice","country":"Czech Republic"},
{"id":701,"label":"43851 Lakeland Alley","description":"Queenstown","country":"South Africa"},
{"id":702,"label":"88 Pankratz Junction","description":"Tochio-honchō","country":"Japan"},
{"id":703,"label":"158 Oriole Plaza","description":"Orzesze","country":"Poland"},
{"id":704,"label":"5 La Follette Parkway","description":"Strogino","country":"Russia"},
{"id":705,"label":"7 Ramsey Park","description":"Nossa Senhora de Machede","country":"Portugal"},
{"id":706,"label":"02 Mallard Park","description":"Futian","country":"China"},
{"id":707,"label":"01391 Orin Plaza","description":"Ciganaria","country":"Indonesia"},
{"id":708,"label":"5581 Ruskin Avenue","description":"Zhaojia","country":"China"},
{"id":709,"label":"0 Mayer Park","description":"Ḩalḩūl","country":"Palestinian Territory"},
{"id":710,"label":"7 Sherman Park","description":"Cincinnati","country":"United States"},
{"id":711,"label":"48940 Shasta Terrace","description":"Hemudu","country":"China"},
{"id":712,"label":"59 Dennis Hill","description":"Mocoa","country":"Colombia"},
{"id":713,"label":"95 Sycamore Park","description":"Messina","country":"Italy"},
{"id":714,"label":"096 Jay Drive","description":"Bojongsari","country":"Indonesia"},
{"id":715,"label":"4405 Westerfield Place","description":"Novobiryusinskiy","country":"Russia"},
{"id":716,"label":"8851 Longview Center","description":"Xichangmen","country":"China"},
{"id":717,"label":"829 Mallory Park","description":"Thị Trấn Quan Hóa","country":"Vietnam"},
{"id":718,"label":"23764 Debs Point","description":"Huayllo","country":"Peru"},
{"id":719,"label":"36335 Dexter Alley","description":"Tegalgunung","country":"Indonesia"},
{"id":720,"label":"0 Hayes Place","description":"L’vovskiy","country":"Russia"},
{"id":721,"label":"8 Vahlen Way","description":"Mojorembun","country":"Indonesia"},
{"id":722,"label":"09 Northwestern Drive","description":"Saint Andrews","country":"Canada"},
{"id":723,"label":"5 Schmedeman Street","description":"Maradi","country":"Niger"},
{"id":724,"label":"5021 Manufacturers Point","description":"Sadabumi","country":"Indonesia"},
{"id":725,"label":"00 Vidon Center","description":"Frakulla e Madhe","country":"Albania"},
{"id":726,"label":"33 Almo Pass","description":"Shiyaogou","country":"China"},
{"id":727,"label":"1 Stone Corner Avenue","description":"Mukdahan","country":"Thailand"},
{"id":728,"label":"0 Sundown Junction","description":"São Gotardo","country":"Brazil"},
{"id":729,"label":"37500 Thierer Road","description":"Bayt Līd","country":"Palestinian Territory"},
{"id":730,"label":"9570 Grover Junction","description":"Guhua","country":"China"},
{"id":731,"label":"42 Ohio Crossing","description":"Guoyuan","country":"China"},
{"id":732,"label":"48 Fair Oaks Street","description":"Arlöv","country":"Sweden"},
{"id":733,"label":"9790 Main Pass","description":"Cinunjang","country":"Indonesia"},
{"id":734,"label":"19 Mcbride Point","description":"Siewierz","country":"Poland"},
{"id":735,"label":"803 Canary Way","description":"Skotoússa","country":"Greece"},
{"id":736,"label":"36 Dayton Plaza","description":"Ban Rangsit","country":"Thailand"},
{"id":737,"label":"814 Magdeline Hill","description":"Miraflores","country":"Portugal"},
{"id":738,"label":"6 7th Crossing","description":"Chamical","country":"Argentina"},
{"id":739,"label":"6277 Roxbury Junction","description":"Plaju","country":"Indonesia"},
{"id":740,"label":"65 Derek Hill","description":"Barras","country":"Brazil"},
{"id":741,"label":"4 Old Shore Point","description":"Yerevan","country":"Armenia"},
{"id":742,"label":"60773 Ruskin Street","description":"Rushanzhai","country":"China"},
{"id":743,"label":"892 Jackson Park","description":"Thala","country":"Tunisia"},
{"id":744,"label":"96652 Reindahl Street","description":"Wschowa","country":"Poland"},
{"id":745,"label":"3 Sachs Circle","description":"Tangjiawan","country":"China"},
{"id":746,"label":"905 Washington Hill","description":"Lidu","country":"China"},
{"id":747,"label":"71 Shasta Way","description":"Belas","country":"Portugal"},
{"id":748,"label":"490 Spaight Place","description":"Sepulu","country":"Indonesia"},
{"id":749,"label":"037 Vernon Court","description":"Naha-shi","country":"Japan"},
{"id":750,"label":"106 Havey Terrace","description":"Babakankiray","country":"Indonesia"},
{"id":751,"label":"1272 Fulton Parkway","description":"Tegalsari","country":"Indonesia"},
{"id":752,"label":"96290 Fuller Drive","description":"Kamionka","country":"Poland"},
{"id":753,"label":"85680 Duke Pass","description":"Władysławowo","country":"Poland"},
{"id":754,"label":"036 Maple Wood Plaza","description":"Qādirpur Rān","country":"Pakistan"},
{"id":755,"label":"28 Dryden Point","description":"Skhira","country":"Tunisia"},
{"id":756,"label":"71 7th Court","description":"Palmas","country":"Brazil"},
{"id":757,"label":"7455 Norway Maple Drive","description":"Chegang","country":"China"},
{"id":758,"label":"62 Red Cloud Avenue","description":"Nakhon Pathom","country":"Thailand"},
{"id":759,"label":"20111 Superior Way","description":"San Isidro","country":"Mexico"},
{"id":760,"label":"50840 5th Terrace","description":"Gezan","country":"China"},
{"id":761,"label":"4 Blue Bill Park Parkway","description":"Kangar","country":"Malaysia"},
{"id":762,"label":"2 Warrior Crossing","description":"Nanxing","country":"China"},
{"id":763,"label":"70 Lakewood Junction","description":"Lysekil","country":"Sweden"},
{"id":764,"label":"17660 Thierer Road","description":"Lasek","country":"Poland"},
{"id":765,"label":"12900 Green Ridge Crossing","description":"Gândara","country":"Portugal"},
{"id":766,"label":"5 Merrick Place","description":"Seltjarnarnes","country":"Iceland"},
{"id":767,"label":"7 Laurel Court","description":"Changliu","country":"China"},
{"id":768,"label":"934 Claremont Terrace","description":"Kalahang","country":"Indonesia"},
{"id":769,"label":"445 Mosinee Lane","description":"Xiashu","country":"China"},
{"id":770,"label":"9842 Morning Center","description":"Huizhou","country":"China"},
{"id":771,"label":"09903 Schiller Court","description":"Jönköping","country":"Sweden"},
{"id":772,"label":"72 Morning Plaza","description":"Xiangshan","country":"China"},
{"id":773,"label":"395 Garrison Park","description":"Changlu","country":"China"},
{"id":774,"label":"190 Pankratz Road","description":"Trabulheira","country":"Portugal"},
{"id":775,"label":"68206 Bunker Hill Pass","description":"Mangkon Daja","country":"Indonesia"},
{"id":776,"label":"9367 Eagle Crest Road","description":"Mityana","country":"Uganda"},
{"id":777,"label":"238 Anthes Crossing","description":"Adrasmon","country":"Tajikistan"},
{"id":778,"label":"7 Rigney Drive","description":"Ila Orangun","country":"Nigeria"},
{"id":779,"label":"61010 Manitowish Way","description":"Carnot","country":"Central African Republic"},
{"id":780,"label":"44608 Larry Point","description":"Senggreng","country":"Indonesia"},
{"id":781,"label":"88 Debra Park","description":"Darungan","country":"Indonesia"},
{"id":782,"label":"07 Vera Lane","description":"Hexiangqiao","country":"China"},
{"id":783,"label":"9004 Stone Corner Crossing","description":"Mirebalais","country":"Haiti"},
{"id":784,"label":"0 Mallory Circle","description":"Loudun","country":"France"},
{"id":785,"label":"363 Norway Maple Drive","description":"Yuewan","country":"China"},
{"id":786,"label":"82 West Drive","description":"Kampot","country":"Cambodia"},
{"id":787,"label":"792 Bartelt Plaza","description":"Alcaldedíaz","country":"Panama"},
{"id":788,"label":"67 Kim Terrace","description":"Bang Rak","country":"Thailand"},
{"id":789,"label":"167 Warner Center","description":"Nakonde","country":"Zambia"},
{"id":790,"label":"642 Clarendon Drive","description":"Houston","country":"United States"},
{"id":791,"label":"4416 Forster Lane","description":"Colorado Springs","country":"United States"},
{"id":792,"label":"76 Luster Point","description":"Kvänum","country":"Sweden"},
{"id":793,"label":"02 Badeau Plaza","description":"Bacheng","country":"China"},
{"id":794,"label":"62777 Forster Crossing","description":"Rislane","country":"Morocco"},
{"id":795,"label":"0412 Ruskin Lane","description":"Erie","country":"United States"},
{"id":796,"label":"4 Banding Trail","description":"Río Grande","country":"Dominican Republic"},
{"id":797,"label":"28 Warner Way","description":"Anda","country":"Philippines"},
{"id":798,"label":"9 Toban Avenue","description":"Kinnula","country":"Finland"},
{"id":799,"label":"02 Parkside Park","description":"El Fureidīs","country":"Israel"},
{"id":800,"label":"8613 Eastwood Street","description":"Banyo","country":"Cameroon"},
{"id":801,"label":"35938 Sauthoff Drive","description":"Lukhovka","country":"Russia"},
{"id":802,"label":"0 Northfield Parkway","description":"Claveria","country":"Philippines"},
{"id":803,"label":"69316 Petterle Circle","description":"Shangtang","country":"China"},
{"id":804,"label":"514 Kennedy Street","description":"Tân Việt","country":"Vietnam"},
{"id":805,"label":"0411 Oak Valley Circle","description":"Ortega","country":"Colombia"},
{"id":806,"label":"3 Schmedeman Circle","description":"Lidun","country":"China"},
{"id":807,"label":"7 Eagle Crest Way","description":"Agua Fría","country":"Honduras"},
{"id":808,"label":"673 Merrick Drive","description":"Cibodas","country":"Indonesia"},
{"id":809,"label":"6 Golf Course Drive","description":"Södertälje","country":"Sweden"},
{"id":810,"label":"0 Beilfuss Way","description":"Daraitan","country":"Philippines"},
{"id":811,"label":"8 Express Plaza","description":"‘Aşīrah al Qiblīyah","country":"Palestinian Territory"},
{"id":812,"label":"4802 Florence Parkway","description":"Norsborg","country":"Sweden"},
{"id":813,"label":"228 Buhler Parkway","description":"Fukui-shi","country":"Japan"},
{"id":814,"label":"64 Anhalt Center","description":"Tabuating","country":"Philippines"},
{"id":815,"label":"0055 4th Center","description":"Bastos","country":"Brazil"},
{"id":816,"label":"5 Erie Street","description":"Oodweyne","country":"Somalia"},
{"id":817,"label":"61377 Talisman Crossing","description":"Guyang","country":"China"},
{"id":818,"label":"6521 Hoffman Park","description":"Cikawunggading","country":"Indonesia"},
{"id":819,"label":"58863 Evergreen Hill","description":"Chang’an","country":"China"},
{"id":820,"label":"2 Lawn Hill","description":"Tsovazard","country":"Armenia"},
{"id":821,"label":"349 Lillian Avenue","description":"Vichadero","country":"Uruguay"},
{"id":822,"label":"853 Cordelia Avenue","description":"Mrganush","country":"Armenia"},
{"id":823,"label":"61 Hudson Alley","description":"Agios Dimitrios","country":"Greece"},
{"id":824,"label":"77 Buell Point","description":"Przecław","country":"Poland"},
{"id":825,"label":"293 Dexter Road","description":"Cikandang","country":"Indonesia"},
{"id":826,"label":"262 West Lane","description":"Ladário","country":"Brazil"},
{"id":827,"label":"379 Northland Point","description":"Watubura","country":"Indonesia"},
{"id":828,"label":"63 Sachtjen Alley","description":"Amio","country":"Philippines"},
{"id":829,"label":"54371 Sommers Center","description":"Chahannao","country":"China"},
{"id":830,"label":"81060 Summerview Junction","description":"Zhixia","country":"China"},
{"id":831,"label":"2 Leroy Circle","description":"Guayabal","country":"Venezuela"},
{"id":832,"label":"98743 Lawn Drive","description":"El Arenal","country":"Mexico"},
{"id":833,"label":"9 Banding Lane","description":"Lüderitz","country":"Namibia"},
{"id":834,"label":"4 Johnson Center","description":"Petaling Jaya","country":"Malaysia"},
{"id":835,"label":"6563 Southridge Terrace","description":"Lenešice","country":"Czech Republic"},
{"id":836,"label":"0 Dixon Place","description":"Al Burayqah","country":"Libya"},
{"id":837,"label":"37916 Rowland Street","description":"Sexiong","country":"China"},
{"id":838,"label":"94416 Melrose Place","description":"Ostrowite","country":"Poland"},
{"id":839,"label":"01 Eastwood Way","description":"Courelas Bravas","country":"Portugal"},
{"id":840,"label":"66077 Mayfield Trail","description":"Yunlong","country":"China"},
{"id":841,"label":"307 Moose Way","description":"Baisha","country":"China"},
{"id":842,"label":"4030 Eggendart Place","description":"Laoxialu","country":"China"},
{"id":843,"label":"60 Waxwing Crossing","description":"Palaiochóri","country":"Greece"},
{"id":844,"label":"27981 Express Court","description":"Boroon","country":"Philippines"},
{"id":845,"label":"47 Mayer Avenue","description":"Hingatungan","country":"Philippines"},
{"id":846,"label":"313 Pleasure Plaza","description":"Changsu","country":"South Korea"},
{"id":847,"label":"38580 Sugar Way","description":"Kagawasan","country":"Philippines"},
{"id":848,"label":"3 Boyd Trail","description":"Petite Rivière de Nippes","country":"Haiti"},
{"id":849,"label":"277 Nobel Terrace","description":"Naurskaya","country":"Russia"},
{"id":850,"label":"7880 Manley Park","description":"Hwado","country":"South Korea"},
{"id":851,"label":"98869 Lyons Lane","description":"Gostynin","country":"Poland"},
{"id":852,"label":"4594 Summerview Point","description":"Jagüey Grande","country":"Cuba"},
{"id":853,"label":"36 Briar Crest Way","description":"Magisterial","country":"Mexico"},
{"id":854,"label":"8226 School Road","description":"Varāmīn","country":"Iran"},
{"id":855,"label":"9 Hallows Street","description":"Solna","country":"Sweden"},
{"id":856,"label":"03475 Westend Pass","description":"Luxi","country":"China"},
{"id":857,"label":"175 Oneill Circle","description":"Hinunangan","country":"Philippines"},
{"id":858,"label":"01 Loomis Court","description":"Wengang","country":"China"},
{"id":859,"label":"8 Dahle Trail","description":"Luhe","country":"China"},
{"id":860,"label":"0 Beilfuss Way","description":"Susuman","country":"Russia"},
{"id":861,"label":"8120 Toban Park","description":"Changyi","country":"China"},
{"id":862,"label":"2143 Shopko Junction","description":"Daru","country":"Sierra Leone"},
{"id":863,"label":"42 Shelley Road","description":"Kundung","country":"Indonesia"},
{"id":864,"label":"29384 Bultman Alley","description":"Mingelchaur","country":"Azerbaijan"},
{"id":865,"label":"9 Warrior Place","description":"Sandakan","country":"Malaysia"},
{"id":866,"label":"0403 4th Alley","description":"Kedungringin","country":"Indonesia"},
{"id":867,"label":"39 2nd Lane","description":"Vigo","country":"Spain"},
{"id":868,"label":"66198 West Lane","description":"Huwan","country":"China"},
{"id":869,"label":"9 Starling Place","description":"Tulsa","country":"United States"},
{"id":870,"label":"7 Texas Place","description":"Tall Salḩab","country":"Syria"},
{"id":871,"label":"453 Veith Parkway","description":"Agoo","country":"Philippines"},
{"id":872,"label":"367 Bowman Road","description":"La Unión","country":"Guatemala"},
{"id":873,"label":"6328 Burning Wood Center","description":"Lins","country":"Brazil"},
{"id":874,"label":"31 Becker Court","description":"Yeniköy","country":"Turkey"},
{"id":875,"label":"5 La Follette Crossing","description":"Port Glaud","country":"Seychelles"},
{"id":876,"label":"66338 Hoffman Hill","description":"Sipirok","country":"Indonesia"},
{"id":877,"label":"6698 Northport Place","description":"Rafaḩ","country":"Egypt"},
{"id":878,"label":"606 East Junction","description":"Séléa","country":"Comoros"},
{"id":879,"label":"49 Northport Circle","description":"Skellefteå","country":"Sweden"},
{"id":880,"label":"543 Lillian Street","description":"Guangshun","country":"China"},
{"id":881,"label":"8 Charing Cross Road","description":"El Paraiso","country":"Mexico"},
{"id":882,"label":"1 Vermont Road","description":"Tours","country":"France"},
{"id":883,"label":"214 Portage Center","description":"Orerokpe","country":"Nigeria"},
{"id":884,"label":"78 Merrick Point","description":"Danyang","country":"China"},
{"id":885,"label":"22088 Oriole Drive","description":"Guling","country":"China"},
{"id":886,"label":"81 Jenna Alley","description":"Rio Meão","country":"Portugal"},
{"id":887,"label":"13 Quincy Avenue","description":"Montenegro","country":"Brazil"},
{"id":888,"label":"82652 Caliangt Center","description":"Rejowinangun","country":"Indonesia"},
{"id":889,"label":"28572 Hermina Pass","description":"Rūjayb","country":"Palestinian Territory"},
{"id":890,"label":"23683 Carberry Trail","description":"Chrysó","country":"Greece"},
{"id":891,"label":"60887 Colorado Hill","description":"Makata","country":"Malawi"},
{"id":892,"label":"4 Warner Street","description":"Sendai","country":"Japan"},
{"id":893,"label":"094 Crest Line Way","description":"Vällingby","country":"Sweden"},
{"id":894,"label":"7 Lyons Alley","description":"Cileueur","country":"Indonesia"},
{"id":895,"label":"27865 Upham Road","description":"Vayk’","country":"Armenia"},
{"id":896,"label":"92 Dottie Park","description":"Ciudad Barrios","country":"El Salvador"},
{"id":897,"label":"47 Red Cloud Road","description":"Lekaj","country":"Albania"},
{"id":898,"label":"6 Charing Cross Place","description":"Lazaro Cardenas","country":"Mexico"},
{"id":899,"label":"330 Farragut Alley","description":"Hesperange","country":"Luxembourg"},
{"id":900,"label":"92 Heffernan Drive","description":"Cinyumput","country":"Indonesia"},
{"id":901,"label":"536 Burning Wood Hill","description":"Mafa","country":"Nigeria"},
{"id":902,"label":"8352 Nancy Way","description":"Zambujeira","country":"Portugal"},
{"id":903,"label":"07 Lakeland Court","description":"Phra Yuen","country":"Thailand"},
{"id":904,"label":"19 Moulton Terrace","description":"San Isidro","country":"Mexico"},
{"id":905,"label":"07 American Ash Center","description":"Agenebode","country":"Nigeria"},
{"id":906,"label":"94031 Eliot Terrace","description":"Wąbrzeźno","country":"Poland"},
{"id":907,"label":"33516 Petterle Alley","description":"Paços de Ferreira","country":"Portugal"},
{"id":908,"label":"025 Carberry Center","description":"Liulimiao","country":"China"},
{"id":909,"label":"29 Nancy Way","description":"Bacun","country":"China"},
{"id":910,"label":"8 Anhalt Road","description":"Niemodlin","country":"Poland"},
{"id":911,"label":"541 Buhler Circle","description":"Alicante/Alacant","country":"Spain"},
{"id":912,"label":"7515 Fordem Place","description":"Pinglin","country":"China"},
{"id":913,"label":"05360 Bluestem Point","description":"Luoshan","country":"China"},
{"id":914,"label":"67023 Fair Oaks Terrace","description":"Palermo","country":"Italy"},
{"id":915,"label":"3322 Union Alley","description":"Longhe","country":"China"},
{"id":916,"label":"5 Cherokee Terrace","description":"Gawul","country":"Indonesia"},
{"id":917,"label":"2529 Morrow Court","description":"Tha Bo","country":"Thailand"},
{"id":918,"label":"5 Mayfield Alley","description":"Tongshan","country":"China"},
{"id":919,"label":"60852 Holy Cross Crossing","description":"Wangong","country":"China"},
{"id":920,"label":"6 Erie Way","description":"Haoshui","country":"China"},
{"id":921,"label":"32 Acker Alley","description":"Novoselë","country":"Albania"},
{"id":922,"label":"4456 Haas Terrace","description":"Peresvet","country":"Russia"},
{"id":923,"label":"818 Lawn Junction","description":"Kubangwaru","country":"Indonesia"},
{"id":924,"label":"329 Nancy Place","description":"Zákynthos","country":"Greece"},
{"id":925,"label":"584 Springs Point","description":"Piancheng","country":"China"},
{"id":926,"label":"312 Logan Court","description":"Saint-Lambert-de-Lauzon","country":"Canada"},
{"id":927,"label":"5 Bellgrove Terrace","description":"Xinyang","country":"China"},
{"id":928,"label":"5 Mallard Way","description":"Tawau","country":"Malaysia"},
{"id":929,"label":"3501 Dwight Center","description":"Huoli","country":"China"},
{"id":930,"label":"4608 Tony Junction","description":"Goshogawara","country":"Japan"},
{"id":931,"label":"7798 Dahle Way","description":"Xuhang","country":"China"},
{"id":932,"label":"09 Stephen Road","description":"Shancheng","country":"China"},
{"id":933,"label":"58795 Namekagon Place","description":"Az̧ Z̧a‘āyin","country":"Qatar"},
{"id":934,"label":"26 Merry Plaza","description":"Ostrów Lubelski","country":"Poland"},
{"id":935,"label":"3558 Killdeer Pass","description":"Tisco","country":"Peru"},
{"id":936,"label":"46773 North Street","description":"Sison","country":"Philippines"},
{"id":937,"label":"03313 Sugar Point","description":"Floreşti","country":"Moldova"},
{"id":938,"label":"4 South Place","description":"Huangcun","country":"China"},
{"id":939,"label":"68832 Ronald Regan Hill","description":"Talok","country":"Indonesia"},
{"id":940,"label":"14557 Golf View Junction","description":"Saint-Louis du Sud","country":"Haiti"},
{"id":941,"label":"7225 Hoepker Parkway","description":"Tangwei","country":"China"},
{"id":942,"label":"6022 Linden Park","description":"Villa Ángela","country":"Argentina"},
{"id":943,"label":"13509 Northfield Parkway","description":"Cential","country":"Portugal"},
{"id":944,"label":"93 Muir Point","description":"Bisert’","country":"Russia"},
{"id":945,"label":"305 Westend Way","description":"Cigaras","country":"Philippines"},
{"id":946,"label":"01015 Maryland Lane","description":"Grecheskoye","country":"Russia"},
{"id":947,"label":"9 Havey Place","description":"Lobão","country":"Portugal"},
{"id":948,"label":"352 Lindbergh Hill","description":"Koloniya Zastav’ye","country":"Ukraine"},
{"id":949,"label":"0 Mesta Alley","description":"Manique de Baixo","country":"Portugal"},
{"id":950,"label":"0702 Lotheville Parkway","description":"Bonoua","country":"Ivory Coast"},
{"id":951,"label":"98 Graceland Road","description":"Sanlei","country":"China"},
{"id":952,"label":"1578 Oak Valley Parkway","description":"Placer","country":"Philippines"},
{"id":953,"label":"241 New Castle Center","description":"Shuitian","country":"China"},
{"id":954,"label":"546 2nd Way","description":"Danderyd","country":"Sweden"},
{"id":955,"label":"844 Spaight Lane","description":"Roi Et","country":"Thailand"},
{"id":956,"label":"5 Lillian Pass","description":"Askeaton","country":"Ireland"},
{"id":957,"label":"1 Westport Street","description":"Cengjia","country":"China"},
{"id":958,"label":"8103 Stephen Hill","description":"Cravinhos","country":"Brazil"},
{"id":959,"label":"978 New Castle Hill","description":"Takayama","country":"Japan"},
{"id":960,"label":"92 Manufacturers Avenue","description":"San Patricio","country":"Paraguay"},
{"id":961,"label":"02438 7th Hill","description":"Hanyuan","country":"China"},
{"id":962,"label":"899 Mcbride Park","description":"Pindorama","country":"Brazil"},
{"id":963,"label":"13444 Washington Road","description":"Nakhon Sawan","country":"Thailand"},
{"id":964,"label":"04390 Lien Place","description":"Bancroft","country":"Canada"},
{"id":965,"label":"4 Gulseth Hill","description":"Mahdalynivka","country":"Ukraine"},
{"id":966,"label":"52162 Truax Point","description":"Hubynykha","country":"Ukraine"},
{"id":967,"label":"7 Knutson Plaza","description":"Huayuan","country":"China"},
{"id":968,"label":"28 Orin Center","description":"Mashi","country":"China"},
{"id":969,"label":"3502 Di Loreto Center","description":"Yafran","country":"Libya"},
{"id":970,"label":"4365 Macpherson Parkway","description":"Blagoevgrad","country":"Bulgaria"},
{"id":971,"label":"977 Boyd Circle","description":"Kotlovka","country":"Russia"},
{"id":972,"label":"26 Corscot Alley","description":"Ribeiro","country":"Portugal"},
{"id":973,"label":"26966 Vermont Plaza","description":"Ban Kruat","country":"Thailand"},
{"id":974,"label":"9769 Pine View Hill","description":"Hanyin Chengguanzhen","country":"China"},
{"id":975,"label":"78639 Schiller Trail","description":"Sandweiler","country":"Luxembourg"},
{"id":976,"label":"02108 Fallview Avenue","description":"Lavezares","country":"Philippines"},
{"id":977,"label":"0 Pierstorff Parkway","description":"Växjö","country":"Sweden"},
{"id":978,"label":"7040 Summit Alley","description":"Megulung","country":"Indonesia"},
{"id":979,"label":"26632 Graedel Street","description":"Kushima","country":"Japan"},
{"id":980,"label":"30395 Bonner Road","description":"Manis Mekarwangi","country":"Indonesia"},
{"id":981,"label":"65726 Bartillon Circle","description":"Moyuan","country":"China"},
{"id":982,"label":"35533 Union Lane","description":"Houston","country":"United States"},
{"id":983,"label":"68 Sunbrook Alley","description":"Huashan","country":"China"},
{"id":984,"label":"4274 John Wall Circle","description":"Bastan","country":"Russia"},
{"id":985,"label":"624 Basil Plaza","description":"Serrana","country":"Brazil"},
{"id":986,"label":"8641 Brown Street","description":"Qingnianlu","country":"China"},
{"id":987,"label":"44 Farragut Drive","description":"Huntington","country":"United States"},
{"id":988,"label":"689 Porter Street","description":"Mranggen","country":"Indonesia"},
{"id":989,"label":"51221 Hudson Park","description":"Cacoal","country":"Brazil"},
{"id":990,"label":"38639 Mendota Center","description":"Póvoa","country":"Portugal"},
{"id":991,"label":"41 Shoshone Court","description":"Ozërsk","country":"Russia"},
{"id":992,"label":"927 North Parkway","description":"Neringa","country":"Lithuania"},
{"id":993,"label":"90 Surrey Hill","description":"Xidianzi","country":"China"},
{"id":994,"label":"97 Sherman Trail","description":"Lijia","country":"China"},
{"id":995,"label":"0867 Ohio Hill","description":"Mayo Belwa","country":"Nigeria"},
{"id":996,"label":"2 Hollow Ridge Junction","description":"Igbeti","country":"Nigeria"},
{"id":997,"label":"1225 Buena Vista Lane","description":"Xinye","country":"China"},
{"id":998,"label":"8014 Melrose Parkway","description":"Bailadores","country":"Venezuela"},
{"id":999,"label":"1112 Fairview Park","description":"Pindi Gheb","country":"Pakistan"},
{"id":1000,"label":"0405 Prentice Lane","description":"Ruzhany","country":"Belarus"}]